[
    {
    "name": "Pelagia Aloyse Katunzi",
    "work": "poetess",
    "topics": "reproductive right",
    "suggestion": "WHAT LOAD IS THIS WITHOUT A RELIEVER? WHAT SUGAR IS THIS THAT CONTAINS POISON?",
    "lang": "Kiswahili",
    "year": 2000,
    "years_dec": "2000s",
    "country": "Tanzania",
    "birth_place": "",
    "Coordinate_LAT": -6.450302903,
    "Coordinate_LONG": 34.9558311,
    "color":"#a2e8d4",
    "Source": "Amandina Lihamba , Fulata L . Moyo , M.M . Mulokozi, Naomi L. Shitemi, Saida Yahya-Othman(2007). Women writing africa: the eastern region. Feminist Press at the City University of New York."
  },
  {
    "name": "Beta Aida",
    "work": "♀",
    "topics": "reproductive right",
    "suggestion": "APOTO THE GIRL",
    "lang": "Acoli",
    "year": 2001,
    "years_dec": "2000s",
    "country": "Uganda",
    "birth_place": "Acoliland",
    "Coordinate_LAT": 3.271622726,
    "Coordinate_LONG": 32.68281109,
    "color":"#a2e8d4",
    "Source": "Amandina Lihamba , Fulata L . Moyo , M.M . Mulokozi, Naomi L. Shitemi, Saida Yahya-Othman(2007). Women writing africa: the eastern region. Feminist Press at the City University of New York."
  }
]
